synthetic/__init__.py
synthetic/cli.py
synthetic/consts.py
synthetic/distances.py
synthetic/evo.py
synthetic/generator.py
synthetic/net.py
synthetic/prog.py
synthetic/stats.py
synthetic/utils.py
synthetic/commands/__init__.py
synthetic/commands/command.py
synthetic/commands/compare.py
synthetic/commands/const.py
synthetic/commands/eval_distance.py
synthetic/commands/evo.py
synthetic/commands/fit.py
synthetic/commands/gen.py
synthetic/commands/prune.py
synthetic/commands/rand_gen.py
synthetic/tests/__init__.py
synthetic/tests/graphs.py
synthetic/tests/test_distances.py
synthetic/tests/test_evo.py
synthetic/tests/test_generator.py
synthetic/tests/test_prog.py
synthetic/tests/test_stats.py
synthetic-0.0.1.dist-info/AUTHORS
synthetic-0.0.1.dist-info/LICENSE
synthetic-0.0.1.dist-info/METADATA
synthetic-0.0.1.dist-info/WHEEL
synthetic-0.0.1.dist-info/entry_points.txt
synthetic-0.0.1.dist-info/top_level.txt
synthetic-0.0.1.dist-info/RECORD
