Metadata-Version: 2.1
Name: synthetic
Version: 0.0.1
Summary: Symbolic generators for complex networks
Home-page: http://ai4socialscience.github.io/synthetic/
Author: Telmo Menezes et al.
Author-email: telmo@telmomenezes.net
License: UNKNOWN
Platform: UNKNOWN
Classifier: Development Status :: 3 - Alpha
Classifier: Programming Language :: Python :: 3
Classifier: License :: OSI Approved :: MIT License
Classifier: Operating System :: OS Independent
Classifier: Environment :: Console
Classifier: Intended Audience :: Science/Research
Classifier: Topic :: Scientific/Engineering :: Artificial Intelligence
Classifier: Topic :: Scientific/Engineering :: Bio-Informatics
Classifier: Topic :: Scientific/Engineering :: Information Analysis
Classifier: Topic :: Scientific/Engineering :: Mathematics
Classifier: Topic :: Sociology
Requires-Dist: numpy
Requires-Dist: python-igraph
Requires-Dist: pyemd
Requires-Dist: progressbar2
Requires-Dist: termcolor
Requires-Dist: jupyter
Provides-Extra: dev
Requires-Dist: sphinx ; extra == 'dev'
Requires-Dist: sphinx-rtd-theme ; extra == 'dev'
